omega_index_py3/__init__.py
omega_index_py3/omgidx.py
omega_index_py3-0.3.1.dist-info/LICENSE.txt
omega_index_py3-0.3.1.dist-info/METADATA
omega_index_py3-0.3.1.dist-info/WHEEL
omega_index_py3-0.3.1.dist-info/top_level.txt
omega_index_py3-0.3.1.dist-info/RECORD
